beni/__init__.py
beni/__main__.py
beni-0.4.4.dist-info/entry_points.txt
beni-0.4.4.dist-info/LICENSE
beni-0.4.4.dist-info/WHEEL
beni-0.4.4.dist-info/METADATA
beni-0.4.4.dist-info/RECORD
