Metadata-Version: 2.1
Name: beni
Version: 0.4.4
Summary: Generate environment.yml from pyproject.toml
Home-page: https://github.com/quansight-labs/beni
Author: Saul Shanabrook and Philipp A.
Author-email: s.shanabrook@gmail.com
Requires-Python: >=3.8
Classifier: License :: OSI Approved :: MIT License
Requires-Dist: pyyaml
Requires-Dist: typeguard
Requires-Dist: packaging
Requires-Dist: tqdm
Requires-Dist: flit-core >=2,<4
Requires-Dist: platformdirs
Requires-Dist: pre-commit ; extra == "dev"
Requires-Dist: ipython ; extra == "dev"
Requires-Dist: pytest ; extra == "test"
Provides-Extra: dev
Provides-Extra: test
